zastro/__init__.py
zastro-0.1.dist-info/DESCRIPTION.rst
zastro-0.1.dist-info/METADATA
zastro-0.1.dist-info/RECORD
zastro-0.1.dist-info/WHEEL
zastro-0.1.dist-info/metadata.json
zastro-0.1.dist-info/top_level.txt
