Metadata-Version: 2.0
Name: zastro
Version: 0.1
Summary: the collection of codes I use frequently for my work 
Home-page: http://github.com/zabop/zastro
Author: Pal Szabo
Author-email: szabopal96@gmail.com
License: MIT
Platform: UNKNOWN
